sqlalchemy_ds_manager/__init__.py
sqlalchemy_ds_manager/datasource.json
sqlalchemy_ds_manager/example.py
sqlalchemy_ds_manager/example_with_cache.py
sqlalchemy_ds_manager/cache/__init__.py
sqlalchemy_ds_manager/cache/file.py
sqlalchemy_ds_manager/datasource/__init__.py
sqlalchemy_ds_manager/datasource/manager.py
sqlalchemy_ds_manager/helper/__init__.py
sqlalchemy_ds_manager/helper/utils.py
sqlalchemy_ds_manager/provider/__init__.py
sqlalchemy_ds_manager/provider/interface.py
sqlalchemy_ds_manager/provider/oracle.py
sqlalchemy_ds_manager/provider/sql_server.py
sqlalchemy_ds_manager-0.0.1.dist-info/METADATA
sqlalchemy_ds_manager-0.0.1.dist-info/WHEEL
sqlalchemy_ds_manager-0.0.1.dist-info/licenses/LICENSE
sqlalchemy_ds_manager-0.0.1.dist-info/RECORD
