Metadata-Version: 2.1
Name: sqlalchemy-ds-manager
Version: 0.0.1
Summary: SqlAlchemy DS Manager: A simple datasource manager for SqlAlchemy using json file and cache manager for your sql statement
Project-URL: Homepage, https://github.com/jnguyen0220/sqlalchemy_ds_manager
Project-URL: Bug Tracker, https://github.com/jnguyen0220/sqlalchemy_ds_manager/issues
Author-email: Jonny Nguyen <jonny_nguyen@outlook.com>
License-File: LICENSE
Classifier: License :: OSI Approved :: MIT License
Classifier: Operating System :: OS Independent
Classifier: Programming Language :: Python :: 3
Requires-Python: >=3.7
Requires-Dist: oracledb
Requires-Dist: pymssql
Requires-Dist: sqlalchemy
